intelmq_webinput_csv/__init__.py
intelmq_webinput_csv/serve.py
intelmq_webinput_csv/version.py
intelmq_webinput_csv-0.5.0.data/scripts/webinput-adduser
webinput_session/__init__.py
webinput_session/config.py
webinput_session/files.py
webinput_session/session.py
webinput_session/setup.py
intelmq_webinput_csv-0.5.0.dist-info/AGPL-3.0.txt
intelmq_webinput_csv-0.5.0.dist-info/METADATA
intelmq_webinput_csv-0.5.0.dist-info/WHEEL
intelmq_webinput_csv-0.5.0.dist-info/top_level.txt
intelmq_webinput_csv-0.5.0.dist-info/RECORD
