Metadata-Version: 2.1
Name: intelmq-webinput-csv
Version: 0.5.0
Summary: This is a simple web interface allowing the user to insert data into intelmq's pipelines interactively with preview from the parser.
Home-page: https://github.com/Intevation/intelmq-certbund-contact
Author: Intevation GmbH
Author-email: info@intevation.de
Maintainer: Raimund Renkert
Maintainer-email: raimund.renkert@intevation.de
License: AGPLv3
Keywords: incident handling cert csirt
Platform: UNKNOWN
License-File: LICENSES/AGPL-3.0.txt
Requires-Dist: hug
